cosinesimilarity/__init__.py
cosinesimilarity/cls_token_embedding.py
cosinesimilarity/cosine.py
cosinesimilarity/sentence_embedding.py
cosinesimilarity/sentence_similarity.py
cosinesimilarity/similarity_functions.py
cosine_similarity-0.1.2.dist-info/LICENSE.txt
cosine_similarity-0.1.2.dist-info/METADATA
cosine_similarity-0.1.2.dist-info/WHEEL
cosine_similarity-0.1.2.dist-info/top_level.txt
cosine_similarity-0.1.2.dist-info/RECORD
