Metadata-Version: 2.1
Name: cosine-similarity
Version: 0.1.2
Summary: This package help you to calculate similarity of texts.
Home-page: https://github.com/avikdas29
Author: Avik Das
Author-email: avik_das_2017@cba.isb.edu
License: UNKNOWN
Project-URL: Bug Tracker, https://github.com/avikdas29
Platform: UNKNOWN
Classifier: Programming Language :: Python :: 2
Classifier: License :: OSI Approved :: MIT License
Classifier: Operating System :: OS Independent
Requires-Python: >=2.0
License-File: LICENSE.txt
